{"time":1722354142698,"in.index":"tensor","in.tensor":[3.0,2.0,1560.0,1020.0,3.0,0.0,0.0,3.0,8.0,1560.0,0.0,47.605,-122.304,1560.0,1728.0,0.0,0.0,0.0],"out._model_split":["{\"model_version\":{\"name\":\"logcontrol\",\"visibility\":\"private\",\"workspace_id\":14,\"conversion\":{\"arch\":\"x86\",\"accel\":\"none\",\"python_version\":\"3.8\",\"requirements\":[],\"framework\":\"onnx\"},\"id\":20,\"image_path\":null,\"status\":\"ready\",\"task_id\":null,\"file_info\":{\"version\":\"b5c3773e-d19a-49bd-bff0-e9cff70b4945\",\"sha\":\"e22a0831aafd9917f3cc87a15ed267797f80e2afa12ad7d8810ca58f173b8cc6\",\"file_name\":\"rf_model.onnx\",\"size\":225818},\"created_on_version\":\"2024.2.0\",\"created_by\":\"john.hansarick@wallaroo.ai\",\"created_at\":null,\"deployed\":false},\"config\":{\"id\":32,\"model_version_id\":20,\"runtime\":\"onnx\",\"filter_threshold\":null,\"tensor_fields\":[\"tensor\"],\"input_schema\":null,\"output_schema\":null,\"batch_config\":null,\"sidekick_uri\":null}}"],"out.variable":[557391.25],"anomaly.count":0}
{"time":1722354142935,"in.index":"tensor","in.tensor":[4.0,3.5,4460.0,16271.0,2.0,0.0,2.0,3.0,11.0,4460.0,0.0,47.5862,-121.97,4540.0,17122.0,13.0,0.0,0.0],"out._model_split":["{\"model_version\":{\"name\":\"logcontrolchallenger01\",\"visibility\":\"private\",\"workspace_id\":14,\"conversion\":{\"arch\":\"x86\",\"accel\":\"none\",\"python_version\":\"3.8\",\"requirements\":[],\"framework\":\"onnx\"},\"id\":21,\"image_path\":null,\"status\":\"ready\",\"task_id\":null,\"file_info\":{\"version\":\"f3a52cc4-0fbc-463e-ae34-7918524083db\",\"sha\":\"31e92d6ccb27b041a324a7ac22cf95d9d6cc3aa7e8263a229f7c4aec4938657c\",\"file_name\":\"xgb_model.onnx\",\"size\":171121},\"created_on_version\":\"2024.2.0\",\"created_by\":\"john.hansarick@wallaroo.ai\",\"created_at\":null,\"deployed\":false},\"config\":{\"id\":34,\"model_version_id\":21,\"runtime\":\"onnx\",\"filter_threshold\":null,\"tensor_fields\":[\"tensor\"],\"input_schema\":null,\"output_schema\":null,\"batch_config\":null,\"sidekick_uri\":null}}"],"out.variable":[1032132.25],"anomaly.count":0}
{"time":1722354143131,"in.index":"tensor","in.tensor":[4.0,2.5,3140.0,12792.0,2.0,0.0,0.0,4.0,9.0,3140.0,0.0,47.3863,-122.156,2510.0,12792.0,37.0,0.0,0.0],"out._model_split":["{\"model_version\":{\"name\":\"logcontrolchallenger01\",\"visibility\":\"private\",\"workspace_id\":14,\"conversion\":{\"arch\":\"x86\",\"accel\":\"none\",\"python_version\":\"3.8\",\"requirements\":[],\"framework\":\"onnx\"},\"id\":21,\"image_path\":null,\"status\":\"ready\",\"task_id\":null,\"file_info\":{\"version\":\"f3a52cc4-0fbc-463e-ae34-7918524083db\",\"sha\":\"31e92d6ccb27b041a324a7ac22cf95d9d6cc3aa7e8263a229f7c4aec4938657c\",\"file_name\":\"xgb_model.onnx\",\"size\":171121},\"created_on_version\":\"2024.2.0\",\"created_by\":\"john.hansarick@wallaroo.ai\",\"created_at\":null,\"deployed\":false},\"config\":{\"id\":34,\"model_version_id\":21,\"runtime\":\"onnx\",\"filter_threshold\":null,\"tensor_fields\":[\"tensor\"],\"input_schema\":null,\"output_schema\":null,\"batch_config\":null,\"sidekick_uri\":null}}"],"out.variable":[462716.9375],"anomaly.count":0}
{"time":1722354143422,"in.index":"tensor","in.tensor":[3.0,2.25,2020.0,3600.0,2.0,0.0,0.0,3.0,8.0,2020.0,0.0,47.6678,-122.165,2070.0,3699.0,16.0,0.0,0.0],"out._model_split":["{\"model_version\":{\"name\":\"logcontrolchallenger01\",\"visibility\":\"private\",\"workspace_id\":14,\"conversion\":{\"arch\":\"x86\",\"accel\":\"none\",\"python_version\":\"3.8\",\"requirements\":[],\"framework\":\"onnx\"},\"id\":21,\"image_path\":null,\"status\":\"ready\",\"task_id\":null,\"file_info\":{\"version\":\"f3a52cc4-0fbc-463e-ae34-7918524083db\",\"sha\":\"31e92d6ccb27b041a324a7ac22cf95d9d6cc3aa7e8263a229f7c4aec4938657c\",\"file_name\":\"xgb_model.onnx\",\"size\":171121},\"created_on_version\":\"2024.2.0\",\"created_by\":\"john.hansarick@wallaroo.ai\",\"created_at\":null,\"deployed\":false},\"config\":{\"id\":34,\"model_version_id\":21,\"runtime\":\"onnx\",\"filter_threshold\":null,\"tensor_fields\":[\"tensor\"],\"input_schema\":null,\"output_schema\":null,\"batch_config\":null,\"sidekick_uri\":null}}"],"out.variable":[607380.9375],"anomaly.count":0}
{"time":1722354143707,"in.index":"tensor","in.tensor":[6.0,4.5,3300.0,7480.0,2.0,0.0,0.0,3.0,8.0,3300.0,0.0,47.6796,-122.104,2470.0,7561.0,34.0,0.0,0.0],"out._model_split":["{\"model_version\":{\"name\":\"logcontrol\",\"visibility\":\"private\",\"workspace_id\":14,\"conversion\":{\"arch\":\"x86\",\"accel\":\"none\",\"python_version\":\"3.8\",\"requirements\":[],\"framework\":\"onnx\"},\"id\":20,\"image_path\":null,\"status\":\"ready\",\"task_id\":null,\"file_info\":{\"version\":\"b5c3773e-d19a-49bd-bff0-e9cff70b4945\",\"sha\":\"e22a0831aafd9917f3cc87a15ed267797f80e2afa12ad7d8810ca58f173b8cc6\",\"file_name\":\"rf_model.onnx\",\"size\":225818},\"created_on_version\":\"2024.2.0\",\"created_by\":\"john.hansarick@wallaroo.ai\",\"created_at\":null,\"deployed\":false},\"config\":{\"id\":32,\"model_version_id\":20,\"runtime\":\"onnx\",\"filter_threshold\":null,\"tensor_fields\":[\"tensor\"],\"input_schema\":null,\"output_schema\":null,\"batch_config\":null,\"sidekick_uri\":null}}"],"out.variable":[725572.5625],"anomaly.count":0}
{"time":1722354143898,"in.index":"tensor","in.tensor":[3.0,2.0,1540.0,8400.0,1.0,0.0,0.0,3.0,7.0,1180.0,360.0,47.6554,-122.129,1550.0,8760.0,46.0,0.0,0.0],"out._model_split":["{\"model_version\":{\"name\":\"logcontrol\",\"visibility\":\"private\",\"workspace_id\":14,\"conversion\":{\"arch\":\"x86\",\"accel\":\"none\",\"python_version\":\"3.8\",\"requirements\":[],\"framework\":\"onnx\"},\"id\":20,\"image_path\":null,\"status\":\"ready\",\"task_id\":null,\"file_info\":{\"version\":\"b5c3773e-d19a-49bd-bff0-e9cff70b4945\",\"sha\":\"e22a0831aafd9917f3cc87a15ed267797f80e2afa12ad7d8810ca58f173b8cc6\",\"file_name\":\"rf_model.onnx\",\"size\":225818},\"created_on_version\":\"2024.2.0\",\"created_by\":\"john.hansarick@wallaroo.ai\",\"created_at\":null,\"deployed\":false},\"config\":{\"id\":32,\"model_version_id\":20,\"runtime\":\"onnx\",\"filter_threshold\":null,\"tensor_fields\":[\"tensor\"],\"input_schema\":null,\"output_schema\":null,\"batch_config\":null,\"sidekick_uri\":null}}"],"out.variable":[552992.0625],"anomaly.count":0}
{"time":1722354144085,"in.index":"tensor","in.tensor":[2.0,1.0,800.0,6016.0,1.0,0.0,0.0,3.0,6.0,800.0,0.0,47.6913,-122.369,1470.0,3734.0,72.0,0.0,0.0],"out._model_split":["{\"model_version\":{\"name\":\"logcontrol\",\"visibility\":\"private\",\"workspace_id\":14,\"conversion\":{\"arch\":\"x86\",\"accel\":\"none\",\"python_version\":\"3.8\",\"requirements\":[],\"framework\":\"onnx\"},\"id\":20,\"image_path\":null,\"status\":\"ready\",\"task_id\":null,\"file_info\":{\"version\":\"b5c3773e-d19a-49bd-bff0-e9cff70b4945\",\"sha\":\"e22a0831aafd9917f3cc87a15ed267797f80e2afa12ad7d8810ca58f173b8cc6\",\"file_name\":\"rf_model.onnx\",\"size\":225818},\"created_on_version\":\"2024.2.0\",\"created_by\":\"john.hansarick@wallaroo.ai\",\"created_at\":null,\"deployed\":false},\"config\":{\"id\":32,\"model_version_id\":20,\"runtime\":\"onnx\",\"filter_threshold\":null,\"tensor_fields\":[\"tensor\"],\"input_schema\":null,\"output_schema\":null,\"batch_config\":null,\"sidekick_uri\":null}}"],"out.variable":[446769.0],"anomaly.count":0}
{"time":1722354144291,"in.index":"tensor","in.tensor":[4.0,3.25,2050.0,5000.0,2.0,0.0,0.0,4.0,8.0,1370.0,680.0,47.6235,-122.298,1720.0,5000.0,27.0,0.0,0.0],"out._model_split":["{\"model_version\":{\"name\":\"logcontrol\",\"visibility\":\"private\",\"workspace_id\":14,\"conversion\":{\"arch\":\"x86\",\"accel\":\"none\",\"python_version\":\"3.8\",\"requirements\":[],\"framework\":\"onnx\"},\"id\":20,\"image_path\":null,\"status\":\"ready\",\"task_id\":null,\"file_info\":{\"version\":\"b5c3773e-d19a-49bd-bff0-e9cff70b4945\",\"sha\":\"e22a0831aafd9917f3cc87a15ed267797f80e2afa12ad7d8810ca58f173b8cc6\",\"file_name\":\"rf_model.onnx\",\"size\":225818},\"created_on_version\":\"2024.2.0\",\"created_by\":\"john.hansarick@wallaroo.ai\",\"created_at\":null,\"deployed\":false},\"config\":{\"id\":32,\"model_version_id\":20,\"runtime\":\"onnx\",\"filter_threshold\":null,\"tensor_fields\":[\"tensor\"],\"input_schema\":null,\"output_schema\":null,\"batch_config\":null,\"sidekick_uri\":null}}"],"out.variable":[630865.5],"anomaly.count":0}
{"time":1722354144506,"in.index":"tensor","in.tensor":[3.0,1.75,1360.0,16000.0,1.0,0.0,0.0,3.0,7.0,1360.0,0.0,47.7583,-122.306,1360.0,12939.0,36.0,0.0,0.0],"out._model_split":["{\"model_version\":{\"name\":\"logcontrolchallenger02\",\"visibility\":\"private\",\"workspace_id\":14,\"conversion\":{\"arch\":\"x86\",\"accel\":\"none\",\"python_version\":\"3.8\",\"requirements\":[],\"framework\":\"onnx\"},\"id\":22,\"image_path\":null,\"status\":\"ready\",\"task_id\":null,\"file_info\":{\"version\":\"2d873927-b47d-4c9f-be9e-762d7b592c1c\",\"sha\":\"ed6065a79d841f7e96307bb20d5ef22840f15da0b587efb51425c7ad60589d6a\",\"file_name\":\"gbr_model.onnx\",\"size\":214380},\"created_on_version\":\"2024.2.0\",\"created_by\":\"john.hansarick@wallaroo.ai\",\"created_at\":null,\"deployed\":false},\"config\":{\"id\":36,\"model_version_id\":22,\"runtime\":\"onnx\",\"filter_threshold\":null,\"tensor_fields\":[\"tensor\"],\"input_schema\":null,\"output_schema\":null,\"batch_config\":null,\"sidekick_uri\":null}}"],"out.variable":[343527.21875],"anomaly.count":0}
{"time":1722354144723,"in.index":"tensor","in.tensor":[5.0,3.0,3320.0,5354.0,2.0,0.0,0.0,3.0,9.0,3320.0,0.0,47.6542,-122.331,2330.0,4040.0,11.0,0.0,0.0],"out._model_split":["{\"model_version\":{\"name\":\"logcontrolchallenger02\",\"visibility\":\"private\",\"workspace_id\":14,\"conversion\":{\"arch\":\"x86\",\"accel\":\"none\",\"python_version\":\"3.8\",\"requirements\":[],\"framework\":\"onnx\"},\"id\":22,\"image_path\":null,\"status\":\"ready\",\"task_id\":null,\"file_info\":{\"version\":\"2d873927-b47d-4c9f-be9e-762d7b592c1c\",\"sha\":\"ed6065a79d841f7e96307bb20d5ef22840f15da0b587efb51425c7ad60589d6a\",\"file_name\":\"gbr_model.onnx\",\"size\":214380},\"created_on_version\":\"2024.2.0\",\"created_by\":\"john.hansarick@wallaroo.ai\",\"created_at\":null,\"deployed\":false},\"config\":{\"id\":36,\"model_version_id\":22,\"runtime\":\"onnx\",\"filter_threshold\":null,\"tensor_fields\":[\"tensor\"],\"input_schema\":null,\"output_schema\":null,\"batch_config\":null,\"sidekick_uri\":null}}"],"out.variable":[1029505.0625],"anomaly.count":0}
{"time":1722354144890,"in.index":"tensor","in.tensor":[4.0,1.0,1060.0,5750.0,1.0,0.0,0.0,3.0,6.0,950.0,110.0,47.6562,-122.389,1790.0,5857.0,110.0,0.0,0.0],"out._model_split":["{\"model_version\":{\"name\":\"logcontrolchallenger01\",\"visibility\":\"private\",\"workspace_id\":14,\"conversion\":{\"arch\":\"x86\",\"accel\":\"none\",\"python_version\":\"3.8\",\"requirements\":[],\"framework\":\"onnx\"},\"id\":21,\"image_path\":null,\"status\":\"ready\",\"task_id\":null,\"file_info\":{\"version\":\"f3a52cc4-0fbc-463e-ae34-7918524083db\",\"sha\":\"31e92d6ccb27b041a324a7ac22cf95d9d6cc3aa7e8263a229f7c4aec4938657c\",\"file_name\":\"xgb_model.onnx\",\"size\":171121},\"created_on_version\":\"2024.2.0\",\"created_by\":\"john.hansarick@wallaroo.ai\",\"created_at\":null,\"deployed\":false},\"config\":{\"id\":34,\"model_version_id\":21,\"runtime\":\"onnx\",\"filter_threshold\":null,\"tensor_fields\":[\"tensor\"],\"input_schema\":null,\"output_schema\":null,\"batch_config\":null,\"sidekick_uri\":null}}"],"out.variable":[483581.25],"anomaly.count":0}
{"time":1722354145079,"in.index":"tensor","in.tensor":[3.0,1.0,1240.0,10800.0,1.0,0.0,0.0,5.0,7.0,1240.0,0.0,47.5233,-122.185,1810.0,10800.0,55.0,0.0,0.0],"out._model_split":["{\"model_version\":{\"name\":\"logcontrol\",\"visibility\":\"private\",\"workspace_id\":14,\"conversion\":{\"arch\":\"x86\",\"accel\":\"none\",\"python_version\":\"3.8\",\"requirements\":[],\"framework\":\"onnx\"},\"id\":20,\"image_path\":null,\"status\":\"ready\",\"task_id\":null,\"file_info\":{\"version\":\"b5c3773e-d19a-49bd-bff0-e9cff70b4945\",\"sha\":\"e22a0831aafd9917f3cc87a15ed267797f80e2afa12ad7d8810ca58f173b8cc6\",\"file_name\":\"rf_model.onnx\",\"size\":225818},\"created_on_version\":\"2024.2.0\",\"created_by\":\"john.hansarick@wallaroo.ai\",\"created_at\":null,\"deployed\":false},\"config\":{\"id\":32,\"model_version_id\":20,\"runtime\":\"onnx\",\"filter_threshold\":null,\"tensor_fields\":[\"tensor\"],\"input_schema\":null,\"output_schema\":null,\"batch_config\":null,\"sidekick_uri\":null}}"],"out.variable":[268856.875],"anomaly.count":0}
{"time":1722354145278,"in.index":"tensor","in.tensor":[2.0,2.5,1785.0,779.0,2.0,0.0,0.0,3.0,7.0,1595.0,190.0,47.5959,-122.198,1780.0,794.0,39.0,0.0,0.0],"out._model_split":["{\"model_version\":{\"name\":\"logcontrolchallenger02\",\"visibility\":\"private\",\"workspace_id\":14,\"conversion\":{\"arch\":\"x86\",\"accel\":\"none\",\"python_version\":\"3.8\",\"requirements\":[],\"framework\":\"onnx\"},\"id\":22,\"image_path\":null,\"status\":\"ready\",\"task_id\":null,\"file_info\":{\"version\":\"2d873927-b47d-4c9f-be9e-762d7b592c1c\",\"sha\":\"ed6065a79d841f7e96307bb20d5ef22840f15da0b587efb51425c7ad60589d6a\",\"file_name\":\"gbr_model.onnx\",\"size\":214380},\"created_on_version\":\"2024.2.0\",\"created_by\":\"john.hansarick@wallaroo.ai\",\"created_at\":null,\"deployed\":false},\"config\":{\"id\":36,\"model_version_id\":22,\"runtime\":\"onnx\",\"filter_threshold\":null,\"tensor_fields\":[\"tensor\"],\"input_schema\":null,\"output_schema\":null,\"batch_config\":null,\"sidekick_uri\":null}}"],"out.variable":[576355.75],"anomaly.count":0}
{"time":1722354145452,"in.index":"tensor","in.tensor":[3.0,1.75,1360.0,18123.0,1.0,0.0,0.0,3.0,8.0,1360.0,0.0,47.4716,-121.756,1570.0,16817.0,31.0,0.0,0.0],"out._model_split":["{\"model_version\":{\"name\":\"logcontrol\",\"visibility\":\"private\",\"workspace_id\":14,\"conversion\":{\"arch\":\"x86\",\"accel\":\"none\",\"python_version\":\"3.8\",\"requirements\":[],\"framework\":\"onnx\"},\"id\":20,\"image_path\":null,\"status\":\"ready\",\"task_id\":null,\"file_info\":{\"version\":\"b5c3773e-d19a-49bd-bff0-e9cff70b4945\",\"sha\":\"e22a0831aafd9917f3cc87a15ed267797f80e2afa12ad7d8810ca58f173b8cc6\",\"file_name\":\"rf_model.onnx\",\"size\":225818},\"created_on_version\":\"2024.2.0\",\"created_by\":\"john.hansarick@wallaroo.ai\",\"created_at\":null,\"deployed\":false},\"config\":{\"id\":32,\"model_version_id\":20,\"runtime\":\"onnx\",\"filter_threshold\":null,\"tensor_fields\":[\"tensor\"],\"input_schema\":null,\"output_schema\":null,\"batch_config\":null,\"sidekick_uri\":null}}"],"out.variable":[252192.90625],"anomaly.count":0}
{"time":1722354145624,"in.index":"tensor","in.tensor":[3.0,1.5,1240.0,8410.0,1.0,0.0,0.0,5.0,6.0,1240.0,0.0,47.753,-122.328,1630.0,8410.0,67.0,0.0,0.0],"out._model_split":["{\"model_version\":{\"name\":\"logcontrol\",\"visibility\":\"private\",\"workspace_id\":14,\"conversion\":{\"arch\":\"x86\",\"accel\":\"none\",\"python_version\":\"3.8\",\"requirements\":[],\"framework\":\"onnx\"},\"id\":20,\"image_path\":null,\"status\":\"ready\",\"task_id\":null,\"file_info\":{\"version\":\"b5c3773e-d19a-49bd-bff0-e9cff70b4945\",\"sha\":\"e22a0831aafd9917f3cc87a15ed267797f80e2afa12ad7d8810ca58f173b8cc6\",\"file_name\":\"rf_model.onnx\",\"size\":225818},\"created_on_version\":\"2024.2.0\",\"created_by\":\"john.hansarick@wallaroo.ai\",\"created_at\":null,\"deployed\":false},\"config\":{\"id\":32,\"model_version_id\":20,\"runtime\":\"onnx\",\"filter_threshold\":null,\"tensor_fields\":[\"tensor\"],\"input_schema\":null,\"output_schema\":null,\"batch_config\":null,\"sidekick_uri\":null}}"],"out.variable":[340764.53125],"anomaly.count":0}
{"time":1722354145794,"in.index":"tensor","in.tensor":[3.0,1.5,1780.0,10196.0,1.0,0.0,0.0,4.0,7.0,1270.0,510.0,47.3375,-122.291,1320.0,7875.0,48.0,0.0,0.0],"out._model_split":["{\"model_version\":{\"name\":\"logcontrolchallenger01\",\"visibility\":\"private\",\"workspace_id\":14,\"conversion\":{\"arch\":\"x86\",\"accel\":\"none\",\"python_version\":\"3.8\",\"requirements\":[],\"framework\":\"onnx\"},\"id\":21,\"image_path\":null,\"status\":\"ready\",\"task_id\":null,\"file_info\":{\"version\":\"f3a52cc4-0fbc-463e-ae34-7918524083db\",\"sha\":\"31e92d6ccb27b041a324a7ac22cf95d9d6cc3aa7e8263a229f7c4aec4938657c\",\"file_name\":\"xgb_model.onnx\",\"size\":171121},\"created_on_version\":\"2024.2.0\",\"created_by\":\"john.hansarick@wallaroo.ai\",\"created_at\":null,\"deployed\":false},\"config\":{\"id\":34,\"model_version_id\":21,\"runtime\":\"onnx\",\"filter_threshold\":null,\"tensor_fields\":[\"tensor\"],\"input_schema\":null,\"output_schema\":null,\"batch_config\":null,\"sidekick_uri\":null}}"],"out.variable":[227109.375],"anomaly.count":0}
{"time":1722354146037,"in.index":"tensor","in.tensor":[3.0,1.5,1220.0,1086.0,3.0,0.0,0.0,3.0,8.0,1220.0,0.0,47.7049,-122.353,1220.0,1422.0,7.0,0.0,0.0],"out._model_split":["{\"model_version\":{\"name\":\"logcontrolchallenger02\",\"visibility\":\"private\",\"workspace_id\":14,\"conversion\":{\"arch\":\"x86\",\"accel\":\"none\",\"python_version\":\"3.8\",\"requirements\":[],\"framework\":\"onnx\"},\"id\":22,\"image_path\":null,\"status\":\"ready\",\"task_id\":null,\"file_info\":{\"version\":\"2d873927-b47d-4c9f-be9e-762d7b592c1c\",\"sha\":\"ed6065a79d841f7e96307bb20d5ef22840f15da0b587efb51425c7ad60589d6a\",\"file_name\":\"gbr_model.onnx\",\"size\":214380},\"created_on_version\":\"2024.2.0\",\"created_by\":\"john.hansarick@wallaroo.ai\",\"created_at\":null,\"deployed\":false},\"config\":{\"id\":36,\"model_version_id\":22,\"runtime\":\"onnx\",\"filter_threshold\":null,\"tensor_fields\":[\"tensor\"],\"input_schema\":null,\"output_schema\":null,\"batch_config\":null,\"sidekick_uri\":null}}"],"out.variable":[344183.53125],"anomaly.count":0}
{"time":1722354146222,"in.index":"tensor","in.tensor":[3.0,1.75,2360.0,8290.0,1.0,0.0,0.0,4.0,7.0,1180.0,1180.0,47.6738,-122.281,1880.0,7670.0,65.0,0.0,0.0],"out._model_split":["{\"model_version\":{\"name\":\"logcontrolchallenger02\",\"visibility\":\"private\",\"workspace_id\":14,\"conversion\":{\"arch\":\"x86\",\"accel\":\"none\",\"python_version\":\"3.8\",\"requirements\":[],\"framework\":\"onnx\"},\"id\":22,\"image_path\":null,\"status\":\"ready\",\"task_id\":null,\"file_info\":{\"version\":\"2d873927-b47d-4c9f-be9e-762d7b592c1c\",\"sha\":\"ed6065a79d841f7e96307bb20d5ef22840f15da0b587efb51425c7ad60589d6a\",\"file_name\":\"gbr_model.onnx\",\"size\":214380},\"created_on_version\":\"2024.2.0\",\"created_by\":\"john.hansarick@wallaroo.ai\",\"created_at\":null,\"deployed\":false},\"config\":{\"id\":36,\"model_version_id\":22,\"runtime\":\"onnx\",\"filter_threshold\":null,\"tensor_fields\":[\"tensor\"],\"input_schema\":null,\"output_schema\":null,\"batch_config\":null,\"sidekick_uri\":null}}"],"out.variable":[708008.25],"anomaly.count":0}
{"time":1722354146402,"in.index":"tensor","in.tensor":[3.0,1.5,1810.0,8232.0,1.0,0.0,0.0,3.0,8.0,1810.0,0.0,47.3195,-122.273,2260.0,8491.0,27.0,0.0,0.0],"out._model_split":["{\"model_version\":{\"name\":\"logcontrolchallenger01\",\"visibility\":\"private\",\"workspace_id\":14,\"conversion\":{\"arch\":\"x86\",\"accel\":\"none\",\"python_version\":\"3.8\",\"requirements\":[],\"framework\":\"onnx\"},\"id\":21,\"image_path\":null,\"status\":\"ready\",\"task_id\":null,\"file_info\":{\"version\":\"f3a52cc4-0fbc-463e-ae34-7918524083db\",\"sha\":\"31e92d6ccb27b041a324a7ac22cf95d9d6cc3aa7e8263a229f7c4aec4938657c\",\"file_name\":\"xgb_model.onnx\",\"size\":171121},\"created_on_version\":\"2024.2.0\",\"created_by\":\"john.hansarick@wallaroo.ai\",\"created_at\":null,\"deployed\":false},\"config\":{\"id\":34,\"model_version_id\":21,\"runtime\":\"onnx\",\"filter_threshold\":null,\"tensor_fields\":[\"tensor\"],\"input_schema\":null,\"output_schema\":null,\"batch_config\":null,\"sidekick_uri\":null}}"],"out.variable":[255264.90625],"anomaly.count":0}
